{
  "version": "7",
  "dialect": "postgresql",
  "entries": [
    {
      "idx": 0,
      "version": "7",
      "when": 1767619340734,
      "tag": "0000_wet_young_avengers",
      "breakpoints": true
    },
    {
      "idx": 1,
      "version": "7",
      "when": 1767708936672,
      "tag": "0001_nasty_post",
      "breakpoints": true
    },
    {
      "idx": 2,
      "version": "7",
      "when": 1767714547327,
      "tag": "0002_silent_the_call",
      "breakpoints": true
    },
    {
      "idx": 3,
      "version": "7",
      "when": 1772968834703,
      "tag": "0003_stiff_wraith",
      "breakpoints": true
    },
    {
      "idx": 4,
      "version": "7",
      "when": 1773585710064,
      "tag": "0004_watery_king_bedlam",
      "breakpoints": true
    },
    {
      "idx": 5,
      "version": "7",
      "when": 1773768357686,
      "tag": "0005_functions",
      "breakpoints": true
    }
  ]
}